Metadata-Version: 2.1
Name: django-tables2-ajax
Version: 1.0
Summary: django-tables2 but with AJAX searching.
Home-page: https://github.com/LegendaryFire/django-tables2-ajax
Author: Tristan Balon
License: UNKNOWN
Platform: UNKNOWN
Classifier: Programming Language :: Python :: 3
Classifier: Framework :: Django :: 3.0
Classifier: Environment :: Web Environment
Classifier: License :: OSI Approved :: MIT License
Classifier: Intended Audience :: Developers
Classifier: Operating System :: OS Independent
License-File: LICENSE
